setup.py
src/__init__.py
src/itpy.py
itpy-0.0.1.dist-info/METADATA
itpy-0.0.1.dist-info/WHEEL
itpy-0.0.1.dist-info/licenses/LICENSE.txt
itpy-0.0.1.dist-info/RECORD
